{"cameraMode":{"drawMode":0,"name":"Shaded","section":"Shading Mode"},"sceneLighting":true,"audioPlay":false,"sceneViewState":{"m_AlwaysRefresh":false,"showFog":true,"showSkybox":true,"showFlares":true,"showImageEffects":true,"showParticleSystems":true,"showVisualEffectGraphs":true,"m_FxEnabled":true},"in2DMode":false,"pivot":{"x":1.1396217346191407,"y":-2.231874465942383,"z":-2.2277450561523439},"rotation":{"x":-0.07818500697612763,"y":0.9143694043159485,"z":-0.3351287543773651,"w":-0.2133214771747589},"size":6.789734363555908,"orthographic":false}